gather_scrobble/__init__.py
gather_scrobble/cli.py
gather_scrobble/config.py
gather_scrobble/info.py
gather_scrobble/scrobble.py
gather_scrobble/test.py
gather_scrobble/utils.py
gather_scrobble-0.1.1.dist-info/LICENSE
gather_scrobble-0.1.1.dist-info/METADATA
gather_scrobble-0.1.1.dist-info/WHEEL
gather_scrobble-0.1.1.dist-info/entry_points.txt
gather_scrobble-0.1.1.dist-info/top_level.txt
gather_scrobble-0.1.1.dist-info/RECORD
