Metadata-Version: 2.1
Name: gather-scrobble
Version: 0.1.1
Summary: Gather Scrobble - Scrobble your last.fm or Spotify activity to the Gather status.
Home-page: https://github.com/pyanderson/gather-scrobble
Author: Anderson de Sousa Lima
Author-email: hello@pyanderson.dev
License: MIT
Keywords: gather,gather-town,lastfm,spotify,scrobble
Classifier: Development Status :: 5 - Production/Stable
Classifier: Intended Audience :: Developers
Classifier: License :: OSI Approved :: MIT License
Classifier: Natural Language :: English
Classifier: Programming Language :: Python :: 3
Classifier: Programming Language :: Python :: 3.4
Classifier: Programming Language :: Python :: 3.5
Classifier: Programming Language :: Python :: 3.6
Classifier: Programming Language :: Python :: 3.7
Classifier: Programming Language :: Python :: 3.8
Classifier: Programming Language :: Python :: 3.9
License-File: LICENSE
Requires-Dist: gather-client-ws (<1)
Requires-Dist: keyring (==23.13.1)
Requires-Dist: keyrings.cryptfile (==1.3.9)
Requires-Dist: python-decouple (==3.8)
Requires-Dist: tabulate (==0.9.0)
Requires-Dist: pylast (==5.1.0)
Requires-Dist: spotipy (==2.22.1)
Requires-Dist: docopt (==0.6.2)
